{"success":true,"vote":{"id":1458,"item_number":"91","title":"Authorize (1) an Emergency Home Repair Program (Program) - as described in Exhibit A in response to the 2021 Texas Severe Winter Storm to provide a grant of up to $10,000.00 per household for emergency repairs for low- to moderate-income persons at or below 80 percent of the area median income; (2) execution of all documents and agreements necessary to implement the Program, including but not limited to agreements with homeowners, contractors, and/or administration agreement(s) for the Program and change orders/amendments; (3) a one-time transfer of funds in an amount not to exceed $2,000,000.00 from the Public Private Partnership Fund to the Emergency Home Repair Program Fund; (4) an increase in appropriations in an amount not to exceed $2,000,000.00 in the Emergency Home Repair Program Fund; (5) a disbursement of funds in an amount not to exceed $2,000,000.00 from the Emergency Home Repair Program Fund in accordance with the Program; and (6) up to 10 percent of the funds to be utilized for program administration - Not to exceed $2,000,000.00 - Financing: Emergency Home Repair Program Fund","description":"Authorize (1) an Emergency Home Repair Program (Program) - as described in Exhibit A in response to the 2021 Texas Severe Winter Storm to provide a grant of up to $10,000.00 per household for emergency repairs for low- to moderate-income persons at or below 80 percent of the area median income; (2) execution of all documents and agreements necessary to implement the Program, including but not limited to agreements with homeowners, contractors, and/or administration agreement(s) for the Program and change orders/amendments; (3) a one-time transfer of funds in an amount not to exceed $2,000,000.00 from the Public Private Partnership Fund to the Emergency Home Repair Program Fund; (4) an increase in appropriations in an amount not to exceed $2,000,000.00 in the Emergency Home Repair Program Fund; (5) a disbursement of funds in an amount not to exceed $2,000,000.00 from the Emergency Home Repair Program Fund in accordance with the Program; and (6) up to 10 percent of the funds to be utilized for program administration - Not to exceed $2,000,000.00 - Financing: Emergency Home Repair Program Fund","outcome":"PASS","ayes":15,"noes":0,"abstain":0,"absent":0,"meeting_id":48,"meeting_date":"2021-02-24","meeting_type":"regular","member_votes":[{"member_id":1,"full_name":"Adam Bazaldua","vote_choice":"AYE"},{"member_id":2,"full_name":"Adam McGough","vote_choice":"AYE"},{"member_id":3,"full_name":"Adam Medrano","vote_choice":"AYE"},{"member_id":4,"full_name":"Cara Mendelsohn","vote_choice":"AYE"},{"member_id":5,"full_name":"Carolyn King Arnold","vote_choice":"AYE"},{"member_id":6,"full_name":"Casey Thomas II","vote_choice":"AYE"},{"member_id":7,"full_name":"Chad West","vote_choice":"AYE"},{"member_id":8,"full_name":"David Blewett","vote_choice":"AYE"},{"member_id":9,"full_name":"Eric Johnson","vote_choice":"AYE"},{"member_id":10,"full_name":"Jaime Resendez","vote_choice":"AYE"},{"member_id":11,"full_name":"Jennifer S. Gates","vote_choice":"AYE"},{"member_id":12,"full_name":"Lee M. Kleinman","vote_choice":"AYE"},{"member_id":13,"full_name":"Omar Narvaez","vote_choice":"AYE"},{"member_id":14,"full_name":"Paula Blackmon","vote_choice":"AYE"},{"member_id":15,"full_name":"Tennell Atkins","vote_choice":"AYE"}],"topics":["Budget & Finance","Contracts & Agreements","Emergency Services"]}}