{"success":true,"vote":{"id":170,"item_number":"5","title":"Authorize an amendment to Resolution No. 18-0279, previously approved on February 14, 2018, the loan agreement and conditional grant agreement with East Dallas Community Organization for construction of 8 eight homes for low and moderate mixed income families to (1) extend the HOME loan agreement and the Bond Conditional Grant Agreement completion date from December 31, 2018 to December 31, 2021; (2) increase the affordable units under the conditional grant agreement from two to six and include reporting/performance thresholds; and (3) reduce the HOME amount of units under the loan agreement from $807,740.00 six to two, reduce funding from up to $900,000.00 to $198,256.00 and close out the appropriation; and (3) amend the terms and include reporting/performance thresholds of the 2012 Bond Conditional Grant Agreement - Financing: No cost consideration to the City","description":"Authorize an amendment to Resolution No. 18-0279, previously approved on February 14, 2018, the loan agreement and conditional grant agreement with East Dallas Community Organization for construction of 8 eight homes for low and moderate mixed income families to (1) extend the HOME loan agreement and the Bond Conditional Grant Agreement completion date from December 31, 2018 to December 31, 2021; (2) increase the affordable units under the conditional grant agreement from two to six and include reporting/performance thresholds; and (3) reduce the HOME amount of units under the loan agreement from $807,740.00 six to two, reduce funding from up to $900,000.00 to $198,256.00 and close out the appropriation; and (3) amend the terms and include reporting/performance thresholds of the 2012 Bond Conditional Grant Agreement - Financing: No cost consideration to the City","outcome":"PASS","ayes":14,"noes":0,"abstain":0,"absent":1,"meeting_id":6,"meeting_date":"2020-02-26","meeting_type":"regular","member_votes":[{"member_id":1,"full_name":"Adam Bazaldua","vote_choice":"AYE"},{"member_id":2,"full_name":"Adam McGough","vote_choice":"AYE"},{"member_id":3,"full_name":"Adam Medrano","vote_choice":"AYE"},{"member_id":4,"full_name":"Cara Mendelsohn","vote_choice":"AYE"},{"member_id":5,"full_name":"Carolyn King Arnold","vote_choice":"AYE"},{"member_id":6,"full_name":"Casey Thomas II","vote_choice":"ABSENT"},{"member_id":7,"full_name":"Chad West","vote_choice":"AYE"},{"member_id":8,"full_name":"David Blewett","vote_choice":"AYE"},{"member_id":9,"full_name":"Eric Johnson","vote_choice":"AYE"},{"member_id":10,"full_name":"Jaime Resendez","vote_choice":"AYE"},{"member_id":11,"full_name":"Jennifer S. Gates","vote_choice":"AYE"},{"member_id":12,"full_name":"Lee M. Kleinman","vote_choice":"AYE"},{"member_id":13,"full_name":"Omar Narvaez","vote_choice":"AYE"},{"member_id":14,"full_name":"Paula Blackmon","vote_choice":"AYE"},{"member_id":15,"full_name":"Tennell Atkins","vote_choice":"AYE"}],"topics":["Budget & Finance","Community Services","Contracts & Agreements"]}}