{"success":true,"vote":{"id":1875,"item_number":"PH1","title":"A public hearing to receive comments to amend the City of Dallas Thoroughfare Plan to (1) change the dimensional classification of Nowitzki Way from Houston Street to Field Street from a special six-lane undivided roadway within 122 feet of right-of-way to a special five-lane divided roadway with two-way cycle track on the southside of the roadway in 122 feet of right-of-way; (2) change the dimensional classification of Field Street from Nowitzki Way to Ashland Street from an existing roadway to a special six-lane divided roadway with two-way cycle track in 100 feet of right-of-way; and (3) change the dimensional classification of Harwood Street from Cedar Springs Road to Woodall Rodgers Freeway from standard four-lane undivided roadway in 60 feet of right-of-way to a special three-lane roadway with two-way cycle track on the westside of roadway in 60 to 62 feet of right-of-way; and, at the close of the public hearing, authorize an ordinance implementing the change - Financing:  This action has no cost consideration to the City (see fiscal information for potential future costs)","description":"A public hearing to receive comments to amend the City of Dallas Thoroughfare Plan to (1) change the dimensional classification of Nowitzki Way from Houston Street to Field Street from a special six-lane undivided roadway within 122 feet of right-of-way to a special five-lane divided roadway with two-way cycle track on the southside of the roadway in 122 feet of right-of-way; (2) change the dimensional classification of Field Street from Nowitzki Way to Ashland Street from an existing roadway to a special six-lane divided roadway with two-way cycle track in 100 feet of right-of-way; and (3) change the dimensional classification of Harwood Street from Cedar Springs Road to Woodall Rodgers Freeway from standard four-lane undivided roadway in 60 feet of right-of-way to a special three-lane roadway with two-way cycle track on the westside of roadway in 60 to 62 feet of right-of-way; and, at the close of the public hearing, authorize an ordinance implementing the change - Financing:  This action has no cost consideration to the City (see fiscal information for potential future costs)","outcome":"PASS","ayes":15,"noes":0,"abstain":0,"absent":0,"meeting_id":60,"meeting_date":"2021-06-09","meeting_type":"regular","member_votes":[{"member_id":1,"full_name":"Adam Bazaldua","vote_choice":"AYE"},{"member_id":2,"full_name":"Adam McGough","vote_choice":"AYE"},{"member_id":3,"full_name":"Adam Medrano","vote_choice":"AYE"},{"member_id":4,"full_name":"Cara Mendelsohn","vote_choice":"AYE"},{"member_id":5,"full_name":"Carolyn King Arnold","vote_choice":"AYE"},{"member_id":6,"full_name":"Casey Thomas II","vote_choice":"AYE"},{"member_id":7,"full_name":"Chad West","vote_choice":"AYE"},{"member_id":8,"full_name":"David Blewett","vote_choice":"AYE"},{"member_id":9,"full_name":"Eric Johnson","vote_choice":"AYE"},{"member_id":10,"full_name":"Jaime Resendez","vote_choice":"AYE"},{"member_id":11,"full_name":"Jennifer S. Gates","vote_choice":"AYE"},{"member_id":12,"full_name":"Lee M. Kleinman","vote_choice":"AYE"},{"member_id":13,"full_name":"Omar Narvaez","vote_choice":"AYE"},{"member_id":14,"full_name":"Paula Blackmon","vote_choice":"AYE"},{"member_id":15,"full_name":"Tennell Atkins","vote_choice":"AYE"}],"topics":["Budget & Finance","Ordinances & Resolutions","Property & Real Estate"]}}