{"success":true,"vote":{"id":230,"item_number":"45","title":"An ordinance amending Chapter 20A, “Fair Housing and Mixed Income Housing,” of the Dallas City Code by amending Sections 20A-2, 20A-3, 20A-8, 20A-14, and 20A-15; (1) providing an updated declaration of policy, (2) providing a definition of sex; (3) providing that the administrator may issue subpoenas to compel the attendance of witnesses or the production of documents; (4) deleting the provision that venue for a civil action brought to enforce a conciliation agreement or a charge under Section 20A-12 is in Dallas County; (5) providing a clarification on calculating the two year period during which an aggrieved person may bring a civil action to seek relief for a discriminatory housing practice; (6) providing a penalty not to exceed $500.00; (7) providing a saving clause; (8) providing a severability clause; and (9) providing an effective date - Financing:  No cost consideration to the City","description":"An ordinance amending Chapter 20A, “Fair Housing and Mixed Income Housing,” of the Dallas City Code by amending Sections 20A-2, 20A-3, 20A-8, 20A-14, and 20A-15; (1) providing an updated declaration of policy, (2) providing a definition of sex; (3) providing that the administrator may issue subpoenas to compel the attendance of witnesses or the production of documents; (4) deleting the provision that venue for a civil action brought to enforce a conciliation agreement or a charge under Section 20A-12 is in Dallas County; (5) providing a clarification on calculating the two year period during which an aggrieved person may bring a civil action to seek relief for a discriminatory housing practice; (6) providing a penalty not to exceed $500.00; (7) providing a saving clause; (8) providing a severability clause; and (9) providing an effective date - Financing:  No cost consideration to the City","outcome":"CONTINUED","ayes":10,"noes":5,"abstain":0,"absent":0,"meeting_id":7,"meeting_date":"2022-02-23","meeting_type":"regular","member_votes":[{"member_id":1,"full_name":"Adam Bazaldua","vote_choice":"NAY"},{"member_id":2,"full_name":"Adam McGough","vote_choice":"AYE"},{"member_id":3,"full_name":"Cara Mendelsohn","vote_choice":"AYE"},{"member_id":4,"full_name":"Carolyn King Arnold","vote_choice":"NAY"},{"member_id":5,"full_name":"Casey Thomas II","vote_choice":"AYE"},{"member_id":6,"full_name":"Chad West","vote_choice":"AYE"},{"member_id":7,"full_name":"Eric Johnson","vote_choice":"AYE"},{"member_id":8,"full_name":"Gay Donnell Willis","vote_choice":"NAY"},{"member_id":9,"full_name":"Jaime Resendez","vote_choice":"AYE"},{"member_id":10,"full_name":"Jaynie Shultz","vote_choice":"NAY"},{"member_id":11,"full_name":"Jesse Moreno","vote_choice":"AYE"},{"member_id":12,"full_name":"Omar Narvaez","vote_choice":"AYE"},{"member_id":13,"full_name":"Paul Ridley","vote_choice":"AYE"},{"member_id":14,"full_name":"Paula Blackmon","vote_choice":"NAY"},{"member_id":15,"full_name":"Tennell Atkins","vote_choice":"AYE"}],"topics":["Budget & Finance","Contracts & Agreements","Housing"]}}