{"success":true,"vote":{"id":5661,"item_number":"26","title":"Authorize Supplemental Agreement No. 2 to the professional services contract with VRX, Inc. for the design of additional paving, drainage, water and wastewater main improvements for the West Red Bird Lane Bridge over Woody Branch Creek Project - Not to exceed $207,085.00, from $335,166.68 to $542,251.68 - Financing: 2023 Certificate of Obligation ($183,470.00), Water Capital Improvement G Fund ($17,711.25), and Wastewater Capital Improvement F Fund ($5,903.75)","description":"Authorize Supplemental Agreement No. 2 to the professional services contract with VRX, Inc. for the design of additional paving, drainage, water and wastewater main improvements for the West Red Bird Lane Bridge over Woody Branch Creek Project - Not to exceed $207,085.00, from $335,166.68 to $542,251.68 - Financing: 2023 Certificate of Obligation ($183,470.00), Water Capital Improvement G Fund ($17,711.25), and Wastewater Capital Improvement F Fund ($5,903.75)","outcome":"PASS","ayes":15,"noes":0,"abstain":0,"absent":0,"meeting_id":181,"meeting_date":"2024-08-14","meeting_type":"regular","member_votes":[{"member_id":1,"full_name":"Adam Bazaldua","vote_choice":"AYE"},{"member_id":4,"full_name":"Cara Mendelsohn","vote_choice":"AYE"},{"member_id":5,"full_name":"Carolyn King Arnold","vote_choice":"AYE"},{"member_id":7,"full_name":"Chad West","vote_choice":"AYE"},{"member_id":9,"full_name":"Eric Johnson","vote_choice":"AYE"},{"member_id":16,"full_name":"Gay Donnell Willis","vote_choice":"AYE"},{"member_id":10,"full_name":"Jaime Resendez","vote_choice":"AYE"},{"member_id":17,"full_name":"Jaynie Shultz","vote_choice":"AYE"},{"member_id":18,"full_name":"Jesse Moreno","vote_choice":"AYE"},{"member_id":20,"full_name":"Kathy Stewart","vote_choice":"AYE"},{"member_id":13,"full_name":"Omar Narvaez","vote_choice":"AYE"},{"member_id":19,"full_name":"Paul Ridley","vote_choice":"AYE"},{"member_id":14,"full_name":"Paula Blackmon","vote_choice":"AYE"},{"member_id":15,"full_name":"Tennell Atkins","vote_choice":"AYE"},{"member_id":21,"full_name":"Zarin Gracey","vote_choice":"AYE"}],"topics":["Budget & Finance","Contracts & Agreements","Economic Development"]}}