{"success":true,"vote":{"id":6366,"item_number":"23","title":"Authorize an Advance Funding Agreement with the Texas Department of Transportation (TxDOT) in the amount of $5,342,996.93 for a U.S. Department of Transportation Federal Highway Administration 2022 Highway Safety Improvement Program grant (Agreement No. CSJ 0048-01-070, etc., Assistance Listing No. 20.205) in the amount of $4,132,270.70 as Federal participation for construction, $498,541.53 as State participation for construction and indirect state costs, and $712,184.70 ($412,182.70 for direct state costs paid to TxDOT and an estimated $300,002.00 for design) plus any cost overruns as local participation to construct traffic signal improvements at six intersections (list attached to Agenda Information Sheet) - Total amount of $412,182.70 - Financing: General Fund","description":"Authorize an Advance Funding Agreement with the Texas Department of Transportation (TxDOT) in the amount of $5,342,996.93 for a U.S. Department of Transportation Federal Highway Administration 2022 Highway Safety Improvement Program grant (Agreement No. CSJ 0048-01-070, etc., Assistance Listing No. 20.205) in the amount of $4,132,270.70 as Federal participation for construction, $498,541.53 as State participation for construction and indirect state costs, and $712,184.70 ($412,182.70 for direct state costs paid to TxDOT and an estimated $300,002.00 for design) plus any cost overruns as local participation to construct traffic signal improvements at six intersections (list attached to Agenda Information Sheet) - Total amount of $412,182.70 - Financing: General Fund","outcome":"PASS","ayes":13,"noes":0,"abstain":0,"absent":2,"meeting_id":201,"meeting_date":"2025-01-22","meeting_type":"regular","member_votes":[{"member_id":1,"full_name":"Adam Bazaldua","vote_choice":"AYE"},{"member_id":4,"full_name":"Cara Mendelsohn","vote_choice":"AYE"},{"member_id":5,"full_name":"Carolyn King Arnold","vote_choice":"AYE"},{"member_id":7,"full_name":"Chad West","vote_choice":"AYE"},{"member_id":9,"full_name":"Eric Johnson","vote_choice":"AYE"},{"member_id":16,"full_name":"Gay Donnell Willis","vote_choice":"AYE"},{"member_id":10,"full_name":"Jaime Resendez","vote_choice":"AYE"},{"member_id":17,"full_name":"Jaynie Shultz","vote_choice":"AYE"},{"member_id":18,"full_name":"Jesse Moreno","vote_choice":"AYE"},{"member_id":20,"full_name":"Kathy Stewart","vote_choice":"ABSENT"},{"member_id":13,"full_name":"Omar Narvaez","vote_choice":"AYE"},{"member_id":19,"full_name":"Paul Ridley","vote_choice":"AYE"},{"member_id":14,"full_name":"Paula Blackmon","vote_choice":"ABSENT"},{"member_id":15,"full_name":"Tennell Atkins","vote_choice":"AYE"},{"member_id":21,"full_name":"Zarin Gracey","vote_choice":"AYE"}],"topics":["Budget & Finance","Contracts & Agreements","Health & Safety"]}}