{"success":true,"vote":{"id":923,"item_number":"8","title":"Authorize the first amendment to the Aviation Lease of Land at Dallas Love Field dated May 20, 2016 with DAL Aviation Development Company, LLC (DAL Avitation) to: (1) accommodate the United States Customs and Border Protection operations - Estimated Revenue Foregone: $30,008.06; and (2) authorize payments from the City to DAL Aviation for fire alarm panel upgrades - Not to exceed $15,000.00 - Financing: Aviation Fund","description":"Authorize the first amendment to the Aviation Lease of Land at Dallas Love Field dated May 20, 2016 with DAL Aviation Development Company, LLC (DAL Avitation) to: (1) accommodate the United States Customs and Border Protection operations - Estimated Revenue Foregone: $30,008.06; and (2) authorize payments from the City to DAL Aviation for fire alarm panel upgrades - Not to exceed $15,000.00 - Financing: Aviation Fund","outcome":"PASS","ayes":15,"noes":0,"abstain":0,"absent":0,"meeting_id":35,"meeting_date":"2020-10-28","meeting_type":"regular","member_votes":[{"member_id":1,"full_name":"Adam Bazaldua","vote_choice":"AYE"},{"member_id":2,"full_name":"Adam McGough","vote_choice":"AYE"},{"member_id":3,"full_name":"Adam Medrano","vote_choice":"AYE"},{"member_id":4,"full_name":"Cara Mendelsohn","vote_choice":"AYE"},{"member_id":5,"full_name":"Carolyn King Arnold","vote_choice":"AYE"},{"member_id":6,"full_name":"Casey Thomas II","vote_choice":"AYE"},{"member_id":7,"full_name":"Chad West","vote_choice":"AYE"},{"member_id":8,"full_name":"David Blewett","vote_choice":"AYE"},{"member_id":9,"full_name":"Eric Johnson","vote_choice":"AYE"},{"member_id":10,"full_name":"Jaime Resendez","vote_choice":"AYE"},{"member_id":11,"full_name":"Jennifer S. Gates","vote_choice":"AYE"},{"member_id":12,"full_name":"Lee M. Kleinman","vote_choice":"AYE"},{"member_id":13,"full_name":"Omar Narvaez","vote_choice":"AYE"},{"member_id":14,"full_name":"Paula Blackmon","vote_choice":"AYE"},{"member_id":15,"full_name":"Tennell Atkins","vote_choice":"AYE"}],"topics":["Budget & Finance","Emergency Services","Ordinances & Resolutions"]}}