{"success":true,"meeting":{"id":25,"event_id":"","meeting_date":"2020-08-19","meeting_type":"regular","legistar_url":null,"agenda_url":null,"minutes_url":"https://citysecretary2.dallascityhall.com/pdf/CC2020/081920Min.pdf","video_url":null,"vote_count":2,"non_voted_count":0,"first_reading_count":0,"agenda_item_count":2,"agenda_items":[{"agenda_sequence":0,"item_type":"voted","item_number":"1","title":"Approval of Minutes of the August 5, 2020 City Council Briefing and August 11, 2020 Budget Briefing Meeting","section":"CONSENT","matter_file":null,"matter_type":null,"topics":["Budget & Finance"],"vote":{"id":605,"outcome":"PASS","ayes":15,"noes":0,"abstain":0,"absent":0}},{"agenda_sequence":1,"item_type":"voted","item_number":"2","title":"Consideration of appointments to boards and commissions and the evaluation and duties of board and commission members (List of nominees is available in the City Secretary's Office)\n[STEPHEN EDISON - CHAIR, ANIMAL ADVISORY COMMISSION; SAMMIE BERRY - CHAIR, REINVESTMENT ZONE SEVEN (SPORTS ARENA)]","section":"CONSENT","matter_file":null,"matter_type":null,"topics":["Appointments"],"vote":{"id":606,"outcome":"PASS","ayes":14,"noes":0,"abstain":1,"absent":0}}]}}